nexusLIMS/__init__.py
nexusLIMS/__main__.py
nexusLIMS/cdcs.py
nexusLIMS/config.py
nexusLIMS/instruments.py
nexusLIMS/utils.py
nexusLIMS/version.py
nexusLIMS/builder/__init__.py
nexusLIMS/builder/record_builder.py
nexusLIMS/cli/__init__.py
nexusLIMS/cli/process_records.py
nexusLIMS/db/__init__.py
nexusLIMS/db/engine.py
nexusLIMS/db/enums.py
nexusLIMS/db/models.py
nexusLIMS/db/session_handler.py
nexusLIMS/db/dev/NexusLIMS_db_creation_script.sql
nexusLIMS/db/dev/migrate_db.py
nexusLIMS/dev_scripts/get_file_sizes.py
nexusLIMS/dev_scripts/process_merge_requests.py
nexusLIMS/dev_scripts/update_xslt_files.py
nexusLIMS/dev_scripts/xslt_transform.py
nexusLIMS/extractors/__init__.py
nexusLIMS/extractors/base.py
nexusLIMS/extractors/profiles.py
nexusLIMS/extractors/registry.py
nexusLIMS/extractors/utils.py
nexusLIMS/extractors/xml_serialization.py
nexusLIMS/extractors/assets/extractor_error.png
nexusLIMS/extractors/assets/extractor_error.svg
nexusLIMS/extractors/assets/spectrum_image_logo.svg
nexusLIMS/extractors/assets/spectrum_image_logo.svg.png
nexusLIMS/extractors/plugins/__init__.py
nexusLIMS/extractors/plugins/basic_metadata.py
nexusLIMS/extractors/plugins/digital_micrograph.py
nexusLIMS/extractors/plugins/edax.py
nexusLIMS/extractors/plugins/fei_emi.py
nexusLIMS/extractors/plugins/orion_HIM_tif.py
nexusLIMS/extractors/plugins/quanta_tif.py
nexusLIMS/extractors/plugins/tescan_tif.py
nexusLIMS/extractors/plugins/preview_generators/__init__.py
nexusLIMS/extractors/plugins/preview_generators/hyperspy_preview.py
nexusLIMS/extractors/plugins/preview_generators/image_preview.py
nexusLIMS/extractors/plugins/preview_generators/text_preview.py
nexusLIMS/extractors/plugins/profiles/__init__.py
nexusLIMS/extractors/plugins/profiles/fei_titan_stem_643.py
nexusLIMS/extractors/plugins/profiles/fei_titan_tem_642.py
nexusLIMS/extractors/plugins/profiles/jeol_jem_642.py
nexusLIMS/harvesters/__init__.py
nexusLIMS/harvesters/reservation_event.py
nexusLIMS/harvesters/nemo/__init__.py
nexuslims-2.3.0.dist-info/METADATA
nexuslims-2.3.0.dist-info/WHEEL
nexuslims-2.3.0.dist-info/entry_points.txt
nexuslims-2.3.0.dist-info/licenses/LICENSE
nexuslims-2.3.0.dist-info/RECORD
