Metadata-Version: 2.4
Name: nexusLIMS
Version: 2.3.0
Summary: Electron Microscopy Nexus LIMS project (Datasophos fork)
Project-URL: Homepage, https://github.com/datasophos/NexusLIMS
Project-URL: Repository, https://github.com/datasophos/NexusLIMS.git
Project-URL: Documentation, https://github.com/datasophos/NexusLIMS
Project-URL: Original-NIST-Repository, https://github.com/usnistgov/NexusLIMS.git
Author-email: Joshua Taillon <josh@datasophos.co>
Maintainer-email: Joshua Taillon <josh@datasophos.co>
License: MIT
License-File: LICENSE
Keywords: LIMS,electron-microscopy,materials,microscopy
Classifier: Development Status :: 5 - Production/Stable
Classifier: Intended Audience :: Science/Research
Classifier: Programming Language :: Python :: 3
Classifier: Programming Language :: Python :: 3.11
Classifier: Programming Language :: Python :: 3.12
Classifier: Topic :: Scientific/Engineering
Requires-Python: <3.13,>=3.11
Requires-Dist: alembic>=1.17.2
Requires-Dist: click>=8.1.8
Requires-Dist: defusedxml<1.0.0,>=0.7.1
Requires-Dist: email-validator>=2.3.0
Requires-Dist: exspy>=0.3.2
Requires-Dist: filelock>=3.0.0
Requires-Dist: hyperspy[speed]<3.0.0,>=2.1.0
Requires-Dist: lxml<5.0.0,>=4.9.2
Requires-Dist: pint<1.0.0,>=0.24.0
Requires-Dist: pixstem>=0.4.0
Requires-Dist: pydantic-settings>=2.12.0
Requires-Dist: pydantic[email]>=2.12.0
Requires-Dist: python-benedict<1.0.0,>=0.35.0
Requires-Dist: python-dotenv<1.0.0,>=0.21.0
Requires-Dist: pytz>=2022.7
Requires-Dist: pyxem>=0.21.0
Requires-Dist: rdflib<8.0.0,>=7.0.0
Requires-Dist: requests-ntlm<2.0.0,>=1.1.0
Requires-Dist: requests<3.0.0,>=2.28.1
Requires-Dist: rich>=13.0.0
Requires-Dist: scikit-learn<2.0.0,>=1.2.0
Requires-Dist: sqlmodel>=0.0.31
Requires-Dist: tzlocal>=5.3.1
